fasttext_pybind.cp39-win32.pyd
fasttext/FastText.py
fasttext/__init__.py
fasttext/tests/__init__.py
fasttext/tests/test_configurations.py
fasttext/tests/test_script.py
fasttext/util/__init__.py
fasttext/util/util.py
fasttext_wheel-0.9.2.dist-info/LICENSE
fasttext_wheel-0.9.2.dist-info/METADATA
fasttext_wheel-0.9.2.dist-info/WHEEL
fasttext_wheel-0.9.2.dist-info/top_level.txt
fasttext_wheel-0.9.2.dist-info/RECORD
