Metadata-Version: 2.1
Name: fasttext-wheel
Version: 0.9.2
Summary: fasttext Python bindings
Home-page: https://github.com/facebookresearch/fastText
Author: Onur Celebi
Author-email: celebio@fb.com
License: MIT
Platform: UNKNOWN
Classifier: Development Status :: 3 - Alpha
Classifier: Intended Audience :: Developers
Classifier: Intended Audience :: Science/Research
Classifier: License :: OSI Approved :: MIT License
Classifier: Programming Language :: Python :: 2.7
Classifier: Programming Language :: Python :: 3.4
Classifier: Programming Language :: Python :: 3.5
Classifier: Programming Language :: Python :: 3.6
Classifier: Topic :: Software Development
Classifier: Topic :: Scientific/Engineering
Classifier: Operating System :: Microsoft :: Windows
Classifier: Operating System :: POSIX
Classifier: Operating System :: Unix
Classifier: Operating System :: MacOS
Requires-Dist: numpy
Requires-Dist: pybind11 (>=2.2)
Requires-Dist: setuptools (>=0.7.0)
